agentforum/__init__.py
agentforum/conversations.py
agentforum/errors.py
agentforum/ext/__init__.py
agentforum/ext/llms/__init__.py
agentforum/ext/llms/openai.py
agentforum/forum.py
agentforum/models.py
agentforum/promises.py
agentforum/storage/__init__.py
agentforum/storage/trees.py
agentforum/storage/trees_impl.py
agentforum/typing.py
agentforum/utils.py
agentforum-0.0.10.dist-info/LICENSE
agentforum-0.0.10.dist-info/METADATA
agentforum-0.0.10.dist-info/WHEEL
agentforum-0.0.10.dist-info/RECORD
