Metadata-Version: 2.1
Name: agentforum
Version: 0.0.10
Summary: An asynchronous framework for building LLM-based multi-agent systems in Python, with a focus on trees of immutable messages and token streaming.
License: MIT
Author: Oleksandr Tereshchenko
Author-email: toporok@gmail.com
Requires-Python: >=3.9,<4.0
Classifier: License :: OSI Approved :: MIT License
Classifier: Programming Language :: Python :: 3
Classifier: Programming Language :: Python :: 3.9
Classifier: Programming Language :: Python :: 3.10
Classifier: Programming Language :: Python :: 3.11
Classifier: Programming Language :: Python :: 3.12
Requires-Dist: pydantic (>=2.0.0,<3.0.0)
